MANIFEST.in
README.rst
setup.py
data/.clang-format
data/.gitignore
data/.readthedocs.yml
data/.travis.yml
data/ACKNOWLEDGMENTS.md
data/CHANGES
data/CMakeLists.txt
data/CONTRIBUTING.md
data/LICENSE
data/MANIFEST.in
data/README.md
data/SECURITY.md
data/pkg.sh
data/tox.ini
data/cmake/CheckExtraCompilerFeatures.cmake
data/cmake/CheckIncludesSymbols.cmake
data/cmake/ConfigureSummary.cmake
data/cmake/DefaultCompilerFlags.cmake
data/cmake/FindCython.cmake
data/cmake/FindGSL.cmake
data/cmake/FindLTDL.cmake
data/cmake/FindLibNeurosim.cmake
data/cmake/FindMusic.cmake
data/cmake/FindPythonModule.cmake
data/cmake/FindReadline.cmake
data/cmake/FindSIONlib.cmake
data/cmake/GetTriple.cmake
data/cmake/NestVersionInfo.cmake
data/cmake/ProcessOptions.cmake
data/cmake/UseCython.cmake
data/cmake/WriteStaticModules_h.cmake
data/cmake/CheckFiles/AlphaCXXBug.cxx
data/cmake/CheckFiles/CMathMacros.cxx
data/cmake/CheckFiles/ICE.cxx
data/cmake/CheckFiles/SigUsrIgnored.cxx
data/cmake/CheckFiles/StaticTemplateDeclaration.cxx
data/cmake/CheckFiles/VectorCapacity.cxx
data/cmake/CheckFiles/VectorCapacityDoubling.cxx
data/cmake/CheckFiles/assert_value.c
data/cmake/CheckFiles/check_return_val.sh
data/cmake/CheckFiles/segfault_value.c
data/cmake/CheckFiles/std_isnan.cxx
data/cmake/CheckFiles/std_nan.cxx
data/cmake/Platform/BlueGeneQ_Base.cmake
data/cmake/Platform/BlueGeneQ_GCC.cmake
data/cmake/Platform/BlueGeneQ_XLC.cmake
data/cmake/Platform/Fugaku_FCC.cmake
data/cmake/Platform/Fujitsu-Sparc64.cmake
data/cmake/Platform/JURON_Base.cmake
data/cmake/Platform/JURON_Clang.cmake
data/cmake/Platform/JURON_GCC.cmake
data/cmake/Platform/JURON_XL.cmake
data/debian/changelog
data/debian/compat
data/debian/control
data/debian/copyright
data/debian/info
data/debian/nest.postinst
data/debian/nest.postrm
data/debian/rules
data/debian/source/format
data/doc/CMakeLists.txt
data/doc/README.md
data/doc/copyright_header.cpp
data/doc/copyright_header.py
data/doc/doc_header.txt
data/doc/extractor_userdocs.py
nest_on_square_wheels.egg-info/PKG-INFO
nest_on_square_wheels.egg-info/SOURCES.txt
nest_on_square_wheels.egg-info/dependency_links.txt
nest_on_square_wheels.egg-info/requires.txt
nest_on_square_wheels.egg-info/top_level.txt