Metadata-Version: 2.1
Name: nest-on-square-wheels
Version: 3.0.2
Summary: Python bindings for NEST
Home-page: https://www.nest-simulator.org
Author: The NEST Initiative
Author-email: info@nest-initiative.org
License: GPLv2+
Project-URL: Homepage, https://www.nest-simulator.org/
Project-URL: Bug Reports, https://github.com/nest/nest-simulator/issues
Project-URL: Source, https://github.com/nest/nest-simulator
Project-URL: Documentation, https://nest-simulator.readthedocs.io/
Keywords: nest,simulator,neuroscience,neural,neuron,network,ai,spike,spiking
Platform: UNKNOWN
Classifier: Development Status :: 6 - Mature
Classifier: Programming Language :: Python :: 3.8
Classifier: Programming Language :: Python :: 3.9
Classifier: Intended Audience :: Science/Research
Classifier: Topic :: Scientific/Engineering
Classifier: Topic :: Scientific/Engineering :: Artificial Intelligence
Requires-Python: >=3.8, <4
Provides-Extra: test
